minzhi/__init__.py
minzhi/ae_client.py
minzhi/authorization.py
minzhi/cmdb_client.py
minzhi/local_typeconversion.py
minzhi/cli/__init__.py
minzhi/cli/get_token.py
minzhi_sdk-0.1.26.dist-info/METADATA
minzhi_sdk-0.1.26.dist-info/WHEEL
minzhi_sdk-0.1.26.dist-info/entry_points.txt
minzhi_sdk-0.1.26.dist-info/RECORD
